[
    {
        "id": 1,
        "username": "exkaau",
        "name": "Al-Amin",
        "wage": 37000,
        "vacation": {
            "2026": [],
            "2027": [],
            "2028": []
        }
    },
    {
        "id": 2,
        "username": "jqu453",
        "name": "Adriana",
        "wage": 31500,
        "vacation": {
            "2026": [],
            "2027": [],
            "2028": []
        }
    },
    {
        "id": 3,
        "username": "gjc023",
        "name":  "Christopher",
        "wage": 47000,
        "vacation": {
            "2026": [],
            "2027": [],
            "2028": []
        }
    },
    {
        "id": 4,
        "username": "tbz193",
        "name":  "Ahmed",
        "wage": 27000,
        "vacation": {
            "2026": [],
            "2027": [],
            "2028": []
        }
    },
    {
        "id": 5,
        "username": "isa082",
        "name":  "Isak",
        "wage": 44000,
        "vacation": {
            "2026": [],
            "2027": [],
            "2028": []
        }
    },
    {
        "id": 6,
        "username": "ddf412",
        "name":  "Kalle",
        "wage": 37000,
        "vacation": {
            "2026": [],
            "2027": [],
            "2028": []
        }
    },
    {
        "id": 7,
        "username": "pnf956",
        "name":  "Marcus",
        "wage": 27000,
        "vacation": {
            "2026": [],
            "2027": [],
            "2028": []
        }
    },
    {
        "id": 8,
        "username": "yzt114",
        "name":  "Okan",
        "wage": 39500,
        "vacation": {
            "2026": [],
            "2027": [],
            "2028": []
        }
    },
    {
        "id": 9,
        "username": "uyr674",
        "name":  "Pierre",
        "wage": 37000,
        "vacation": {
            "2026": [],
            "2027": [],
            "2028": []
        }
    },
    {
        "id": 10,
        "username": "mgu229",
        "name":  "Robin",
        "wage": 37000,
        "vacation": {
            "2026": [],
            "2027": [],
            "2028": []
        }
    }
]